anansescanpy/__init__.py
anansescanpy/anansescanpy_export.py
anansescanpy/anansescanpy_import.py
anansescanpy/anansescanpy_motif.py
anansescanpy-1.0.0.dist-info/LICENSE
anansescanpy-1.0.0.dist-info/WHEEL
anansescanpy-1.0.0.dist-info/METADATA
anansescanpy-1.0.0.dist-info/RECORD
