Metadata-Version: 2.1
Name: anansescanpy
Version: 1.0.0
Summary: implementation of scANANSE for scanpy objects in Python
Home-page: https://github.com/Arts-of-coding/AnanseScanpy
License: apache 2.0
Keywords: GRN,single-cell,gene expression,open chromatin,arts-of-coding
Author: J Arts (Arts-of-coding)
Author-email: julian.armando.arts@gmail.com
Requires-Python: >3.8
Classifier: License :: Other/Proprietary License
Classifier: Programming Language :: Python :: 3
Classifier: Programming Language :: Python :: 3.9
Classifier: Programming Language :: Python :: 3.10
Classifier: Programming Language :: Python :: 3.11
Requires-Dist: anndata (>=0.8.0,<0.9.0)
Requires-Dist: numba (>=0.56.3,<0.57.0)
Requires-Dist: numpy (>=1.23.5,<1.24)
Requires-Dist: packaging (>=21.3,<22.0)
Requires-Dist: pandas (>=1.4.4,<2.0.0)
Requires-Dist: scanpy (>=1.9.1,<2.0.0)
Requires-Dist: scipy (>=1.9.1,<2.0.0)
Project-URL: Repository, https://github.com/Arts-of-coding/AnanseScanpy
